coloredlog/__init__.py
coloredlog/color.py
coloredlog-0.2.5.dist-info/LICENSE
coloredlog-0.2.5.dist-info/METADATA
coloredlog-0.2.5.dist-info/WHEEL
coloredlog-0.2.5.dist-info/top_level.txt
coloredlog-0.2.5.dist-info/RECORD
