Metadata-Version: 2.1
Name: coloredlog
Version: 0.2.5
Summary: Colorize your console output.
Home-page: https://github.com/cangyin/coloredlog
Author: CangYin
Author-email: excangyin@gmail.com
License: UNKNOWN
Platform: UNKNOWN
Classifier: Programming Language :: Python :: 3
Classifier: License :: OSI Approved :: MIT License
Classifier: Operating System :: OS Independent
Requires-Python: >=3.6
